odoo/addons/l10n_be_national_number/README.rst
odoo/addons/l10n_be_national_number/__init__.py
odoo/addons/l10n_be_national_number/__manifest__.py
odoo/addons/l10n_be_national_number/data/res_partner_id_category.xml
odoo/addons/l10n_be_national_number/i18n/l10n_be_national_number.pot
odoo/addons/l10n_be_national_number/models/__init__.py
odoo/addons/l10n_be_national_number/models/res_partner.py
odoo/addons/l10n_be_national_number/readme/CONTRIBUTORS.rst
odoo/addons/l10n_be_national_number/readme/DESCRIPTION.rst
odoo/addons/l10n_be_national_number/readme/ROADMAP.rst
odoo/addons/l10n_be_national_number/static/description/icon.png
odoo/addons/l10n_be_national_number/static/description/index.html
odoo12_addon_l10n_be_national_number-12.0.1.0.0.99.dev4.dist-info/METADATA
odoo12_addon_l10n_be_national_number-12.0.1.0.0.99.dev4.dist-info/WHEEL
odoo12_addon_l10n_be_national_number-12.0.1.0.0.99.dev4.dist-info/top_level.txt
odoo12_addon_l10n_be_national_number-12.0.1.0.0.99.dev4.dist-info/RECORD
